confspace/__init__.py
confspace-0.0.2.dist-info/METADATA
confspace-0.0.2.dist-info/WHEEL
confspace-0.0.2.dist-info/top_level.txt
confspace-0.0.2.dist-info/RECORD
