Metadata-Version: 2.1
Name: confspace
Version: 0.0.2
Summary: confspace object for tuning parameter
Home-page: https://github.com/hoonisone/confspace
Author: Hoonisone
Author-email: hoonisone@gmail.com
Classifier: Programming Language :: Python :: 3
Classifier: License :: OSI Approved :: MIT License
Classifier: Operating System :: OS Independent
Requires-Python: >=3.6
